pkg_exporter/__init__.py
pkg_exporter/pkgmanager/__init__.py
pkg_exporter/pkgmanager/apt.py
pkg_exporter/reboot.py
pkg_exporter/textfile.py
pkg_exporter-0.2.7.dist-info/LICENSE
pkg_exporter-0.2.7.dist-info/METADATA
pkg_exporter-0.2.7.dist-info/WHEEL
pkg_exporter-0.2.7.dist-info/entry_points.txt
pkg_exporter-0.2.7.dist-info/RECORD
