Metadata-Version: 2.1
Name: pkg-exporter
Version: 0.2.7
Summary: This project provides an textfile-based exporter for apt-repositories
License: GPL3
Author: Marvin Gaube
Author-email: dev@marvingaube.de
Requires-Python: >=3.6,<4.0
Classifier: License :: Other/Proprietary License
Classifier: Programming Language :: Python :: 3
Classifier: Programming Language :: Python :: 3.6
Classifier: Programming Language :: Python :: 3.7
Classifier: Programming Language :: Python :: 3.8
Classifier: Programming Language :: Python :: 3.9
Classifier: Programming Language :: Python :: 3.10
Classifier: Programming Language :: Python :: 3.11
Requires-Dist: prometheus-client (>=0.15.0,<0.16.0)
